geoconformal/GeoConformalSpatialRegression.py
geoconformal/__init__.py
geoconformal/utils.py
geoconformal-0.1.5.dist-info/licenses/LICENSE
geoconformal-0.1.5.dist-info/METADATA
geoconformal-0.1.5.dist-info/WHEEL
geoconformal-0.1.5.dist-info/top_level.txt
geoconformal-0.1.5.dist-info/RECORD
